[
    {
        "bank_name": "Central Bank of Libya",
        "swift_code": "CBLYLYLX",
        "country": "LY"
    },
    {
        "bank_name": "Libyan Foreign Bank",
        "swift_code": "LFBLLYLX",
        "country": "LY"
    },
    {
        "bank_name": "Jumhouria Bank",
        "swift_code": "JUMHLYLX",
        "country": "LY"
    },
    {
        "bank_name": "National Commercial Bank (NCB)",
        "swift_code": "NCOMLYLX",
        "country": "LY"
    },
    {
        "bank_name": "Mediterranean Bank",
        "swift_code": "MEDILLYX",
        "country": "LY"
    },
    {
        "bank_name": "Bank of Libya and the Arab Foreign Trade",
        "swift_code": "BLAFLYLX",
        "country": "LY"
    },
    {
        "bank_name": "Libya Africa Investment Portfolio",
        "swift_code": "LAIPLYLX",
        "country": "LY"
    },
    {
        "bank_name": "Ahlia Bank",
        "swift_code": "AHLIYLYX",
        "country": "LY"
    },
    {
        "bank_name": "Al-Waha Bank",
        "swift_code": "ALWAHA",
        "country": "LY"
    },
    {
        "bank_name": "Fransabank Libya",
        "swift_code": "FRANSLYX",
        "country": "LY"
    },
    {
        "bank_name": "Al-Takaful Bank",
        "swift_code": "ALTAKFLY",
        "country": "LY"
    },
    {
        "bank_name": "Libya Bank",
        "swift_code": "LYBANKLY",
        "country": "LY"
    },
    {
        "bank_name": "Al-Masraf Bank",
        "swift_code": "ALMASRFC",
        "country": "LY"
    }
]